NoomSmartKeyboard/__init__.py
NoomSmartKeyboard-1.0.0.dist-info/LICENSE
NoomSmartKeyboard-1.0.0.dist-info/METADATA
NoomSmartKeyboard-1.0.0.dist-info/WHEEL
NoomSmartKeyboard-1.0.0.dist-info/top_level.txt
NoomSmartKeyboard-1.0.0.dist-info/RECORD
