Metadata-Version: 2.1
Name: NoomSmartKeyboard
Version: 1.0.0
Summary: Description of my package
Home-page: https://github.com/poommin2543/Noom-Smart-Keyboard
Author: Noom Poommin
Author-email: poommin2543@gmail.com
Classifier: Development Status :: 3 - Alpha
Classifier: Intended Audience :: Developers
Classifier: License :: OSI Approved :: MIT License
Classifier: Programming Language :: Python :: 3
Classifier: Operating System :: Microsoft :: Windows
License-File: LICENSE
Requires-Dist: pywin32
